Metadata-Version: 2.1
Name: twitch-enums
Version: 1.0.0
Summary: Unofficial twitch api enums. (Scopes, Apis)
Home-page: UNKNOWN
Author: notory
Maintainer: notory
License: UNKNOWN
Platform: UNKNOWN
